Workbook
Name L_TAGS: tb_pcm_ativos[tag]
Name L_SETORES: tb_pcm_setores[nome_setor]
Name L_CATEG: tb_pcm_categorias_custo[categoria_custo]
Name L_FAMILIAS: tb_pcm_familias[nome_familia]

Sheet Leia-me
D1: LEIA-ME · GUIA RÁPIDO | F1: Modelos, guias e novidades
D2: PCM-MAN-012 · Orçamento e custos | F2: pcmdireto.me
D3: Leia em 1 minuto, preencha os campos brancos e comece a usar. | F3: Dúvidas e sugestões pelo site
B5: COMO USAR ESTE MODELO
B6: 1 Identifique | D6: 2 Cadastre | E6: 3 Preencha | F6: 4 Imprima e revise
B7: Preencha Elaborado e Aprovado logo abaixo. Vai para o cabeçalho de todas as abas. | D7: Na aba Cadastros, lance TAGs, pessoas e setores uma vez. Eles viram as listas ▼. | E7: Use as abas na ordem do passo a passo. Comece por Orçamento anual. | F7: Cada aba sai em uma folha A4. Mudou o modelo? Registre na aba Revisões.
B9: 1 IDENTIFICAÇÃO DO DOCUMENTO · vai para o cabeçalho de todas as abas | I9: LISTAS DAS SETAS ▼ · valores fixos, não altere
B10: Título do documento | D10: Orçamento e custos | F10: Já vem pronto. Ajuste se quiser. | I10: Categoria custo | J10: Significado
B11: Objetivo | D11: Planejar o orçamento anual da manutenção e acompanhar o realizado pelos lançamentos | I11: categoria_custo | J11: rotulo_categoria
B12: Código do documento | D12: PCM-MAN-012 | I12: MATERIAL | J12: Material
B13: Elaborado por | F13: ✎ preencha | I13: MAO_OBRA | J13: Mão de obra
B14: Aprovado por | F14: ✎ preencha | I14: TERCEIROS | J14: Terceiros
B15: Revisão atual | D15: =IF(COUNTA(tb_pcm_revisoes_modelo[revisao])=0,"-",INDEX(tb_pcm_revisoes_modelo[revisao],COUNTA(tb_pcm_revisoes_modelo[revisao]))) | F15: automático: aba Revisões | I15: OUTROS | J15: Outros
B16: Data da revisão | D16: =IF(COUNTA(tb_pcm_revisoes_modelo[revisao])=0,"",IF(INDEX(tb_pcm_revisoes_modelo[data_revisao],COUNTA(tb_pcm_revisoes_modelo[revisao]))="","",RIGHT("0"&DAY(INDEX(tb_pcm_revisoes_modelo[data_revisao],COUNTA(tb_pcm_revisoes_modelo[revisao]))),2)&"/"&CHOOSE(MONTH(INDEX(tb_pcm_revisoes_modelo[data_revisao],COUNTA(tb_pcm_revisoes_modelo[revisao]))),"Jan","Fev","Mar","Abr","Mai","Jun","Jul","Ago","Set","Out","Nov","Dez")&"/"&YEAR(INDEX(tb_pcm_revisoes_modelo[data_revisao],COUNTA(tb_pcm_revisoes_modelo[revisao]))))) | F16: automático: aba Revisões
B18: 2 PASSO A PASSO · clique no nome da aba para abrir
B19: 1 | C19: Cadastros | D19: Cadastre uma vez TAG, equipamento, família e setor, os setores, as famílias de equipamento. Eles aparecem nas setas ▼ das outras abas.
B20: 2 | C20: Orçamento anual | D20: Escolha o ano e digite o valor orçado de cada categoria em cada mês.
B21: 3 | C21: Lançamentos | D21: Lance cada custo em uma linha: data, TAG, setor, categoria e valor. O realizado do orçamento soma sozinho.
B22: 4 | C22: Acompanhamento | D22: No orçamento, % usado fica verde até 90%, amarelo até 100% e vermelho acima. Filtre por setor no topo, se quiser.
B24: 3 REGRAS RÁPIDAS
B25: ▼ Lista | D25: Clique na célula e escolha na seta. Valor fora da lista é recusado.
B26: Célula branca | D26: Campo para digitar.
B27: Célula cinza | D27: Cálculo automático. Não digite: a fórmula preenche sozinha.
B28: Datas e números | D28: Datas em dd/mm/aaaa; decimais com vírgula. Vazio = sem informação; zero é valor real.
B29: Impressão | D29: Cada aba já está ajustada para uma folha A4. Use Arquivo > Imprimir sem mudar a escala.
D31: SOBRE O PCM DIRETO | F31: pcmdireto.me
D32: Modelos de manutenção prontos para usar, do planejamento ao controle: criticidade, plano, ordem de serviço, indicadores e auditorias. Todos no mesmo padrão, para a equipe aprender uma vez e usar em todos.

Sheet Orçamento anual
C1: ='Leia-me'!$D$10 | N1: ="Rev. "&'Leia-me'!$D$15&" · "&'Leia-me'!$D$16
C2: ="Objetivo: "&'Leia-me'!$D$11 | N2: ="Elaborado: "&'Leia-me'!$D$13&" · Aprovado: "&'Leia-me'!$D$14
A3: Ano ▼ | B3: Setor ou área ▼ (vazio = todos) | F3: Orçado no ano (R$) | I3: Realizado no ano (R$) | L3: Saldo (R$) | O3: % usado
F4: =N12 | I4: =N20 | L4: =F4-I4 | O4: =IF(N(F4)=0,"",I4/F4)
A6: Orçado digite o valor previsto por mês (R$)
A7: Categoria | B7: Jan | C7: Fev | D7: Mar | E7: Abr | F7: Mai | G7: Jun | H7: Jul | I7: Ago | J7: Set | K7: Out | L7: Nov | M7: Dez | N7: Total orçado | O7: Realizado | P7: % usado
A8: Material | N8: =SUM(B8:M8) | O8: =N16 | P8: =IF(N(N8)=0,"",O8/N8)
A9: Mão de obra | N9: =SUM(B9:M9) | O9: =N17 | P9: =IF(N(N9)=0,"",O9/N9)
A10: Terceiros | N10: =SUM(B10:M10) | O10: =N18 | P10: =IF(N(N10)=0,"",O10/N10)
A11: Outros | N11: =SUM(B11:M11) | O11: =N19 | P11: =IF(N(N11)=0,"",O11/N11)
A12: Total do mês | B12: =SUM(B8:B11) | C12: =SUM(C8:C11) | D12: =SUM(D8:D11) | E12: =SUM(E8:E11) | F12: =SUM(F8:F11) | G12: =SUM(G8:G11) | H12: =SUM(H8:H11) | I12: =SUM(I8:I11) | ... N12: =SUM(N8:N11) | O12: =N20 | P12: =IF(N(N12)=0,"",O12/N12)
A14: Realizado vem sozinho da aba Lançamentos (soma por categoria e mês)
A15: Categoria | B15: Jan | C15: Fev | D15: Mar | E15: Abr | F15: Mai | G15: Jun | H15: Jul | I15: Ago | J15: Set | K15: Out | L15: Nov | M15: Dez | N15: Total realizado | O15: Diferença no ano (orçado − realizado)
A16: Material | B16: =IF($B$4="",SUMIFS(tb_pcm_custos[valor_realizado],tb_pcm_custos[data_lancamento],">="&DATE(IF(N($A$4)>0,N($A$4),IF(ISNUMBER(--$A$4),--$A$4,YEAR(TODAY()))),1,1),tb_pcm_custos[data_lancamento],"<="&EOMONTH(DATE(IF(N($A$4)>0,N($A$4),IF(ISNUMBER(--$A$4),--$A$4,YEAR(TODAY()))),1,1),0),tb_pcm_custos[categoria_custo],"MATERIAL"),SUMIFS(tb_pcm_custos[valor_realizado],tb_pcm_custos[data_lancamento],">="&DATE(IF(N($A$4)>0,N($A$4),IF(ISNUMBER(--$A$4),--$A$4,YEAR(TODAY()))),1,1),tb_pcm_custos[data_lancamento],"<="&EOMONTH(DATE(IF(N($A$4)>0,N($A$4),IF(ISNUMBER(--$A$4),--$A$4,YEAR(TODAY()))),1,1),0),tb_pcm_custos[categoria_custo],"MATERIAL",tb_pcm_custos[setor],$B$4)) | C16: =IF($B$4="",SUMIFS(tb_pcm_custos[valor_realizado],tb_pcm_custos[data_lancamento],">="&DATE(IF(N($A$4)>0,N($A$4),IF(ISNUMBER(--$A$4),--$A$4,YEAR(TODAY()))),2,1),tb_pcm_custos[data_lancamento],"<="&EOMONTH(DATE(IF(N($A$4)>0,N($A$4),IF(ISNUMBER(--$A$4),--$A$4,YEAR(TODAY()))),2,1),0),tb_pcm_custos[categoria_custo],"MATERIAL"),SUMIFS(tb_pcm_custos[valor_realizado],tb_pcm_custos[data_lancamento],">="&DATE(IF(N($A$4)>0,N($A$4),IF(ISNUMBER(--$A$4),--$A$4,YEAR(TODAY()))),2,1),tb_pcm_custos[data_lancamento],"<="&EOMONTH(DATE(IF(N($A$4)>0,N($A$4),IF(ISNUMBER(--$A$4),--$A$4,YEAR(TODAY()))),2,1),0),tb_pcm_custos[categoria_custo],"MATERIAL",tb_pcm_custos[setor],$B$4)) | D16: =IF($B$4="",SUMIFS(tb_pcm_custos[valor_realizado],tb_pcm_custos[data_lancamento],">="&DATE(IF(N($A$4)>0,N($A$4),IF(ISNUMBER(--$A$4),--$A$4,YEAR(TODAY()))),3,1),tb_pcm_custos[data_lancamento],"<="&EOMONTH(DATE(IF(N($A$4)>0,N($A$4),IF(ISNUMBER(--$A$4),--$A$4,YEAR(TODAY()))),3,1),0),tb_pcm_custos[categoria_custo],"MATERIAL"),SUMIFS(tb_pcm_custos[valor_realizado],tb_pcm_custos[data_lancamento],">="&DATE(IF(N($A$4)>0,N($A$4),IF(ISNUMBER(--$A$4),--$A$4,YEAR(TODAY()))),3,1),tb_pcm_custos[data_lancamento],"<="&EOMONTH(DATE(IF(N($A$4)>0,N($A$4),IF(ISNUMBER(--$A$4),--$A$4,YEAR(TODAY()))),3,1),0),tb_pcm_custos[categoria_custo],"MATERIAL",tb_pcm_custos[setor],$B$4)) | E16: =IF($B$4="",SUMIFS(tb_pcm_custos[valor_realizado],tb_pcm_custos[data_lancamento],">="&DATE(IF(N($A$4)>0,N($A$4),IF(ISNUMBER(--$A$4),--$A$4,YEAR(TODAY()))),4,1),tb_pcm_custos[data_lancamento],"<="&EOMONTH(DATE(IF(N($A$4)>0,N($A$4),IF(ISNUMBER(--$A$4),--$A$4,YEAR(TODAY()))),4,1),0),tb_pcm_custos[categoria_custo],"MATERIAL"),SUMIFS(tb_pcm_custos[valor_realizado],tb_pcm_custos[data_lancamento],">="&DATE(IF(N($A$4)>0,N($A$4),IF(ISNUMBER(--$A$4),--$A$4,YEAR(TODAY()))),4,1),tb_pcm_custos[data_lancamento],"<="&EOMONTH(DATE(IF(N($A$4)>0,N($A$4),IF(ISNUMBER(--$A$4),--$A$4,YEAR(TODAY()))),4,1),0),tb_pcm_custos[categoria_custo],"MATERIAL",tb_pcm_custos[setor],$B$4)) | F16: =IF($B$4="",SUMIFS(tb_pcm_custos[valor_realizado],tb_pcm_custos[data_lancamento],">="&DATE(IF(N($A$4)>0,N($A$4),IF(ISNUMBER(--$A$4),--$A$4,YEAR(TODAY()))),5,1),tb_pcm_custos[data_lancamento],"<="&EOMONTH(DATE(IF(N($A$4)>0,N($A$4),IF(ISNUMBER(--$A$4),--$A$4,YEAR(TODAY()))),5,1),0),tb_pcm_custos[categoria_custo],"MATERIAL"),SUMIFS(tb_pcm_custos[valor_realizado],tb_pcm_custos[data_lancamento],">="&DATE(IF(N($A$4)>0,N($A$4),IF(ISNUMBER(--$A$4),--$A$4,YEAR(TODAY()))),5,1),tb_pcm_custos[data_lancamento],"<="&EOMONTH(DATE(IF(N($A$4)>0,N($A$4),IF(ISNUMBER(--$A$4),--$A$4,YEAR(TODAY()))),5,1),0),tb_pcm_custos[categoria_custo],"MATERIAL",tb_pcm_custos[setor],$B$4)) | G16: =IF($B$4="",SUMIFS(tb_pcm_custos[valor_realizado],tb_pcm_custos[data_lancamento],">="&DATE(IF(N($A$4)>0,N($A$4),IF(ISNUMBER(--$A$4),--$A$4,YEAR(TODAY()))),6,1),tb_pcm_custos[data_lancamento],"<="&EOMONTH(DATE(IF(N($A$4)>0,N($A$4),IF(ISNUMBER(--$A$4),--$A$4,YEAR(TODAY()))),6,1),0),tb_pcm_custos[categoria_custo],"MATERIAL"),SUMIFS(tb_pcm_custos[valor_realizado],tb_pcm_custos[data_lancamento],">="&DATE(IF(N($A$4)>0,N($A$4),IF(ISNUMBER(--$A$4),--$A$4,YEAR(TODAY()))),6,1),tb_pcm_custos[data_lancamento],"<="&EOMONTH(DATE(IF(N($A$4)>0,N($A$4),IF(ISNUMBER(--$A$4),--$A$4,YEAR(TODAY()))),6,1),0),tb_pcm_custos[categoria_custo],"MATERIAL",tb_pcm_custos[setor],$B$4)) | H16: =IF($B$4="",SUMIFS(tb_pcm_custos[valor_realizado],tb_pcm_custos[data_lancamento],">="&DATE(IF(N($A$4)>0,N($A$4),IF(ISNUMBER(--$A$4),--$A$4,YEAR(TODAY()))),7,1),tb_pcm_custos[data_lancamento],"<="&EOMONTH(DATE(IF(N($A$4)>0,N($A$4),IF(ISNUMBER(--$A$4),--$A$4,YEAR(TODAY()))),7,1),0),tb_pcm_custos[categoria_custo],"MATERIAL"),SUMIFS(tb_pcm_custos[valor_realizado],tb_pcm_custos[data_lancamento],">="&DATE(IF(N($A$4)>0,N($A$4),IF(ISNUMBER(--$A$4),--$A$4,YEAR(TODAY()))),7,1),tb_pcm_custos[data_lancamento],"<="&EOMONTH(DATE(IF(N($A$4)>0,N($A$4),IF(ISNUMBER(--$A$4),--$A$4,YEAR(TODAY()))),7,1),0),tb_pcm_custos[categoria_custo],"MATERIAL",tb_pcm_custos[setor],$B$4)) | I16: =IF($B$4="",SUMIFS(tb_pcm_custos[valor_realizado],tb_pcm_custos[data_lancamento],">="&DATE(IF(N($A$4)>0,N($A$4),IF(ISNUMBER(--$A$4),--$A$4,YEAR(TODAY()))),8,1),tb_pcm_custos[data_lancamento],"<="&EOMONTH(DATE(IF(N($A$4)>0,N($A$4),IF(ISNUMBER(--$A$4),--$A$4,YEAR(TODAY()))),8,1),0),tb_pcm_custos[categoria_custo],"MATERIAL"),SUMIFS(tb_pcm_custos[valor_realizado],tb_pcm_custos[data_lancamento],">="&DATE(IF(N($A$4)>0,N($A$4),IF(ISNUMBER(--$A$4),--$A$4,YEAR(TODAY()))),8,1),tb_pcm_custos[data_lancamento],"<="&EOMONTH(DATE(IF(N($A$4)>0,N($A$4),IF(ISNUMBER(--$A$4),--$A$4,YEAR(TODAY()))),8,1),0),tb_pcm_custos[categoria_custo],"MATERIAL",tb_pcm_custos[setor],$B$4)) | J16: =IF($B$4="",SUMIFS(tb_pcm_custos[valor_realizado],tb_pcm_custos[data_lancamento],">="&DATE(IF(N($A$4)>0,N($A$4),IF(ISNUMBER(--$A$4),--$A$4,YEAR(TODAY()))),9,1),tb_pcm_custos[data_lancamento],"<="&EOMONTH(DATE(IF(N($A$4)>0,N($A$4),IF(ISNUMBER(--$A$4),--$A$4,YEAR(TODAY()))),9,1),0),tb_pcm_custos[categoria_custo],"MATERIAL"),SUMIFS(tb_pcm_custos[valor_realizado],tb_pcm_custos[data_lancamento],">="&DATE(IF(N($A$4)>0,N($A$4),IF(ISNUMBER(--$A$4),--$A$4,YEAR(TODAY()))),9,1),tb_pcm_custos[data_lancamento],"<="&EOMONTH(DATE(IF(N($A$4)>0,N($A$4),IF(ISNUMBER(--$A$4),--$A$4,YEAR(TODAY()))),9,1),0),tb_pcm_custos[categoria_custo],"MATERIAL",tb_pcm_custos[setor],$B$4)) | K16: =IF($B$4="",SUMIFS(tb_pcm_custos[valor_realizado],tb_pcm_custos[data_lancamento],">="&DATE(IF(N($A$4)>0,N($A$4),IF(ISNUMBER(--$A$4),--$A$4,YEAR(TODAY()))),10,1),tb_pcm_custos[data_lancamento],"<="&EOMONTH(DATE(IF(N($A$4)>0,N($A$4),IF(ISNUMBER(--$A$4),--$A$4,YEAR(TODAY()))),10,1),0),tb_pcm_custos[categoria_custo],"MATERIAL"),SUMIFS(tb_pcm_custos[valor_realizado],tb_pcm_custos[data_lancamento],">="&DATE(IF(N($A$4)>0,N($A$4),IF(ISNUMBER(--$A$4),--$A$4,YEAR(TODAY()))),10,1),tb_pcm_custos[data_lancamento],"<="&EOMONTH(DATE(IF(N($A$4)>0,N($A$4),IF(ISNUMBER(--$A$4),--$A$4,YEAR(TODAY()))),10,1),0),tb_pcm_custos[categoria_custo],"MATERIAL",tb_pcm_custos[setor],$B$4)) | L16: =IF($B$4="",SUMIFS(tb_pcm_custos[valor_realizado],tb_pcm_custos[data_lancamento],">="&DATE(IF(N($A$4)>0,N($A$4),IF(ISNUMBER(--$A$4),--$A$4,YEAR(TODAY()))),11,1),tb_pcm_custos[data_lancamento],"<="&EOMONTH(DATE(IF(N($A$4)>0,N($A$4),IF(ISNUMBER(--$A$4),--$A$4,YEAR(TODAY()))),11,1),0),tb_pcm_custos[categoria_custo],"MATERIAL"),SUMIFS(tb_pcm_custos[valor_realizado],tb_pcm_custos[data_lancamento],">="&DATE(IF(N($A$4)>0,N($A$4),IF(ISNUMBER(--$A$4),--$A$4,YEAR(TODAY()))),11,1),tb_pcm_custos[data_lancamento],"<="&EOMONTH(DATE(IF(N($A$4)>0,N($A$4),IF(ISNUMBER(--$A$4),--$A$4,YEAR(TODAY()))),11,1),0),tb_pcm_custos[categoria_custo],"MATERIAL",tb_pcm_custos[setor],$B$4)) | M16: =IF($B$4="",SUMIFS(tb_pcm_custos[valor_realizado],tb_pcm_custos[data_lancamento],">="&DATE(IF(N($A$4)>0,N($A$4),IF(ISNUMBER(--$A$4),--$A$4,YEAR(TODAY()))),12,1),tb_pcm_custos[data_lancamento],"<="&EOMONTH(DATE(IF(N($A$4)>0,N($A$4),IF(ISNUMBER(--$A$4),--$A$4,YEAR(TODAY()))),12,1),0),tb_pcm_custos[categoria_custo],"MATERIAL"),SUMIFS(tb_pcm_custos[valor_realizado],tb_pcm_custos[data_lancamento],">="&DATE(IF(N($A$4)>0,N($A$4),IF(ISNUMBER(--$A$4),--$A$4,YEAR(TODAY()))),12,1),tb_pcm_custos[data_lancamento],"<="&EOMONTH(DATE(IF(N($A$4)>0,N($A$4),IF(ISNUMBER(--$A$4),--$A$4,YEAR(TODAY()))),12,1),0),tb_pcm_custos[categoria_custo],"MATERIAL",tb_pcm_custos[setor],$B$4)) | N16: =SUM(B16:M16) | O16: =N8-N16
A17: Mão de obra | B17: =IF($B$4="",SUMIFS(tb_pcm_custos[valor_realizado],tb_pcm_custos[data_lancamento],">="&DATE(IF(N($A$4)>0,N($A$4),IF(ISNUMBER(--$A$4),--$A$4,YEAR(TODAY()))),1,1),tb_pcm_custos[data_lancamento],"<="&EOMONTH(DATE(IF(N($A$4)>0,N($A$4),IF(ISNUMBER(--$A$4),--$A$4,YEAR(TODAY()))),1,1),0),tb_pcm_custos[categoria_custo],"MAO_OBRA"),SUMIFS(tb_pcm_custos[valor_realizado],tb_pcm_custos[data_lancamento],">="&DATE(IF(N($A$4)>0,N($A$4),IF(ISNUMBER(--$A$4),--$A$4,YEAR(TODAY()))),1,1),tb_pcm_custos[data_lancamento],"<="&EOMONTH(DATE(IF(N($A$4)>0,N($A$4),IF(ISNUMBER(--$A$4),--$A$4,YEAR(TODAY()))),1,1),0),tb_pcm_custos[categoria_custo],"MAO_OBRA",tb_pcm_custos[setor],$B$4)) | C17: =IF($B$4="",SUMIFS(tb_pcm_custos[valor_realizado],tb_pcm_custos[data_lancamento],">="&DATE(IF(N($A$4)>0,N($A$4),IF(ISNUMBER(--$A$4),--$A$4,YEAR(TODAY()))),2,1),tb_pcm_custos[data_lancamento],"<="&EOMONTH(DATE(IF(N($A$4)>0,N($A$4),IF(ISNUMBER(--$A$4),--$A$4,YEAR(TODAY()))),2,1),0),tb_pcm_custos[categoria_custo],"MAO_OBRA"),SUMIFS(tb_pcm_custos[valor_realizado],tb_pcm_custos[data_lancamento],">="&DATE(IF(N($A$4)>0,N($A$4),IF(ISNUMBER(--$A$4),--$A$4,YEAR(TODAY()))),2,1),tb_pcm_custos[data_lancamento],"<="&EOMONTH(DATE(IF(N($A$4)>0,N($A$4),IF(ISNUMBER(--$A$4),--$A$4,YEAR(TODAY()))),2,1),0),tb_pcm_custos[categoria_custo],"MAO_OBRA",tb_pcm_custos[setor],$B$4)) | D17: =IF($B$4="",SUMIFS(tb_pcm_custos[valor_realizado],tb_pcm_custos[data_lancamento],">="&DATE(IF(N($A$4)>0,N($A$4),IF(ISNUMBER(--$A$4),--$A$4,YEAR(TODAY()))),3,1),tb_pcm_custos[data_lancamento],"<="&EOMONTH(DATE(IF(N($A$4)>0,N($A$4),IF(ISNUMBER(--$A$4),--$A$4,YEAR(TODAY()))),3,1),0),tb_pcm_custos[categoria_custo],"MAO_OBRA"),SUMIFS(tb_pcm_custos[valor_realizado],tb_pcm_custos[data_lancamento],">="&DATE(IF(N($A$4)>0,N($A$4),IF(ISNUMBER(--$A$4),--$A$4,YEAR(TODAY()))),3,1),tb_pcm_custos[data_lancamento],"<="&EOMONTH(DATE(IF(N($A$4)>0,N($A$4),IF(ISNUMBER(--$A$4),--$A$4,YEAR(TODAY()))),3,1),0),tb_pcm_custos[categoria_custo],"MAO_OBRA",tb_pcm_custos[setor],$B$4)) | E17: =IF($B$4="",SUMIFS(tb_pcm_custos[valor_realizado],tb_pcm_custos[data_lancamento],">="&DATE(IF(N($A$4)>0,N($A$4),IF(ISNUMBER(--$A$4),--$A$4,YEAR(TODAY()))),4,1),tb_pcm_custos[data_lancamento],"<="&EOMONTH(DATE(IF(N($A$4)>0,N($A$4),IF(ISNUMBER(--$A$4),--$A$4,YEAR(TODAY()))),4,1),0),tb_pcm_custos[categoria_custo],"MAO_OBRA"),SUMIFS(tb_pcm_custos[valor_realizado],tb_pcm_custos[data_lancamento],">="&DATE(IF(N($A$4)>0,N($A$4),IF(ISNUMBER(--$A$4),--$A$4,YEAR(TODAY()))),4,1),tb_pcm_custos[data_lancamento],"<="&EOMONTH(DATE(IF(N($A$4)>0,N($A$4),IF(ISNUMBER(--$A$4),--$A$4,YEAR(TODAY()))),4,1),0),tb_pcm_custos[categoria_custo],"MAO_OBRA",tb_pcm_custos[setor],$B$4)) | F17: =IF($B$4="",SUMIFS(tb_pcm_custos[valor_realizado],tb_pcm_custos[data_lancamento],">="&DATE(IF(N($A$4)>0,N($A$4),IF(ISNUMBER(--$A$4),--$A$4,YEAR(TODAY()))),5,1),tb_pcm_custos[data_lancamento],"<="&EOMONTH(DATE(IF(N($A$4)>0,N($A$4),IF(ISNUMBER(--$A$4),--$A$4,YEAR(TODAY()))),5,1),0),tb_pcm_custos[categoria_custo],"MAO_OBRA"),SUMIFS(tb_pcm_custos[valor_realizado],tb_pcm_custos[data_lancamento],">="&DATE(IF(N($A$4)>0,N($A$4),IF(ISNUMBER(--$A$4),--$A$4,YEAR(TODAY()))),5,1),tb_pcm_custos[data_lancamento],"<="&EOMONTH(DATE(IF(N($A$4)>0,N($A$4),IF(ISNUMBER(--$A$4),--$A$4,YEAR(TODAY()))),5,1),0),tb_pcm_custos[categoria_custo],"MAO_OBRA",tb_pcm_custos[setor],$B$4)) | G17: =IF($B$4="",SUMIFS(tb_pcm_custos[valor_realizado],tb_pcm_custos[data_lancamento],">="&DATE(IF(N($A$4)>0,N($A$4),IF(ISNUMBER(--$A$4),--$A$4,YEAR(TODAY()))),6,1),tb_pcm_custos[data_lancamento],"<="&EOMONTH(DATE(IF(N($A$4)>0,N($A$4),IF(ISNUMBER(--$A$4),--$A$4,YEAR(TODAY()))),6,1),0),tb_pcm_custos[categoria_custo],"MAO_OBRA"),SUMIFS(tb_pcm_custos[valor_realizado],tb_pcm_custos[data_lancamento],">="&DATE(IF(N($A$4)>0,N($A$4),IF(ISNUMBER(--$A$4),--$A$4,YEAR(TODAY()))),6,1),tb_pcm_custos[data_lancamento],"<="&EOMONTH(DATE(IF(N($A$4)>0,N($A$4),IF(ISNUMBER(--$A$4),--$A$4,YEAR(TODAY()))),6,1),0),tb_pcm_custos[categoria_custo],"MAO_OBRA",tb_pcm_custos[setor],$B$4)) | H17: =IF($B$4="",SUMIFS(tb_pcm_custos[valor_realizado],tb_pcm_custos[data_lancamento],">="&DATE(IF(N($A$4)>0,N($A$4),IF(ISNUMBER(--$A$4),--$A$4,YEAR(TODAY()))),7,1),tb_pcm_custos[data_lancamento],"<="&EOMONTH(DATE(IF(N($A$4)>0,N($A$4),IF(ISNUMBER(--$A$4),--$A$4,YEAR(TODAY()))),7,1),0),tb_pcm_custos[categoria_custo],"MAO_OBRA"),SUMIFS(tb_pcm_custos[valor_realizado],tb_pcm_custos[data_lancamento],">="&DATE(IF(N($A$4)>0,N($A$4),IF(ISNUMBER(--$A$4),--$A$4,YEAR(TODAY()))),7,1),tb_pcm_custos[data_lancamento],"<="&EOMONTH(DATE(IF(N($A$4)>0,N($A$4),IF(ISNUMBER(--$A$4),--$A$4,YEAR(TODAY()))),7,1),0),tb_pcm_custos[categoria_custo],"MAO_OBRA",tb_pcm_custos[setor],$B$4)) | I17: =IF($B$4="",SUMIFS(tb_pcm_custos[valor_realizado],tb_pcm_custos[data_lancamento],">="&DATE(IF(N($A$4)>0,N($A$4),IF(ISNUMBER(--$A$4),--$A$4,YEAR(TODAY()))),8,1),tb_pcm_custos[data_lancamento],"<="&EOMONTH(DATE(IF(N($A$4)>0,N($A$4),IF(ISNUMBER(--$A$4),--$A$4,YEAR(TODAY()))),8,1),0),tb_pcm_custos[categoria_custo],"MAO_OBRA"),SUMIFS(tb_pcm_custos[valor_realizado],tb_pcm_custos[data_lancamento],">="&DATE(IF(N($A$4)>0,N($A$4),IF(ISNUMBER(--$A$4),--$A$4,YEAR(TODAY()))),8,1),tb_pcm_custos[data_lancamento],"<="&EOMONTH(DATE(IF(N($A$4)>0,N($A$4),IF(ISNUMBER(--$A$4),--$A$4,YEAR(TODAY()))),8,1),0),tb_pcm_custos[categoria_custo],"MAO_OBRA",tb_pcm_custos[setor],$B$4)) | J17: =IF($B$4="",SUMIFS(tb_pcm_custos[valor_realizado],tb_pcm_custos[data_lancamento],">="&DATE(IF(N($A$4)>0,N($A$4),IF(ISNUMBER(--$A$4),--$A$4,YEAR(TODAY()))),9,1),tb_pcm_custos[data_lancamento],"<="&EOMONTH(DATE(IF(N($A$4)>0,N($A$4),IF(ISNUMBER(--$A$4),--$A$4,YEAR(TODAY()))),9,1),0),tb_pcm_custos[categoria_custo],"MAO_OBRA"),SUMIFS(tb_pcm_custos[valor_realizado],tb_pcm_custos[data_lancamento],">="&DATE(IF(N($A$4)>0,N($A$4),IF(ISNUMBER(--$A$4),--$A$4,YEAR(TODAY()))),9,1),tb_pcm_custos[data_lancamento],"<="&EOMONTH(DATE(IF(N($A$4)>0,N($A$4),IF(ISNUMBER(--$A$4),--$A$4,YEAR(TODAY()))),9,1),0),tb_pcm_custos[categoria_custo],"MAO_OBRA",tb_pcm_custos[setor],$B$4)) | K17: =IF($B$4="",SUMIFS(tb_pcm_custos[valor_realizado],tb_pcm_custos[data_lancamento],">="&DATE(IF(N($A$4)>0,N($A$4),IF(ISNUMBER(--$A$4),--$A$4,YEAR(TODAY()))),10,1),tb_pcm_custos[data_lancamento],"<="&EOMONTH(DATE(IF(N($A$4)>0,N($A$4),IF(ISNUMBER(--$A$4),--$A$4,YEAR(TODAY()))),10,1),0),tb_pcm_custos[categoria_custo],"MAO_OBRA"),SUMIFS(tb_pcm_custos[valor_realizado],tb_pcm_custos[data_lancamento],">="&DATE(IF(N($A$4)>0,N($A$4),IF(ISNUMBER(--$A$4),--$A$4,YEAR(TODAY()))),10,1),tb_pcm_custos[data_lancamento],"<="&EOMONTH(DATE(IF(N($A$4)>0,N($A$4),IF(ISNUMBER(--$A$4),--$A$4,YEAR(TODAY()))),10,1),0),tb_pcm_custos[categoria_custo],"MAO_OBRA",tb_pcm_custos[setor],$B$4)) | L17: =IF($B$4="",SUMIFS(tb_pcm_custos[valor_realizado],tb_pcm_custos[data_lancamento],">="&DATE(IF(N($A$4)>0,N($A$4),IF(ISNUMBER(--$A$4),--$A$4,YEAR(TODAY()))),11,1),tb_pcm_custos[data_lancamento],"<="&EOMONTH(DATE(IF(N($A$4)>0,N($A$4),IF(ISNUMBER(--$A$4),--$A$4,YEAR(TODAY()))),11,1),0),tb_pcm_custos[categoria_custo],"MAO_OBRA"),SUMIFS(tb_pcm_custos[valor_realizado],tb_pcm_custos[data_lancamento],">="&DATE(IF(N($A$4)>0,N($A$4),IF(ISNUMBER(--$A$4),--$A$4,YEAR(TODAY()))),11,1),tb_pcm_custos[data_lancamento],"<="&EOMONTH(DATE(IF(N($A$4)>0,N($A$4),IF(ISNUMBER(--$A$4),--$A$4,YEAR(TODAY()))),11,1),0),tb_pcm_custos[categoria_custo],"MAO_OBRA",tb_pcm_custos[setor],$B$4)) | M17: =IF($B$4="",SUMIFS(tb_pcm_custos[valor_realizado],tb_pcm_custos[data_lancamento],">="&DATE(IF(N($A$4)>0,N($A$4),IF(ISNUMBER(--$A$4),--$A$4,YEAR(TODAY()))),12,1),tb_pcm_custos[data_lancamento],"<="&EOMONTH(DATE(IF(N($A$4)>0,N($A$4),IF(ISNUMBER(--$A$4),--$A$4,YEAR(TODAY()))),12,1),0),tb_pcm_custos[categoria_custo],"MAO_OBRA"),SUMIFS(tb_pcm_custos[valor_realizado],tb_pcm_custos[data_lancamento],">="&DATE(IF(N($A$4)>0,N($A$4),IF(ISNUMBER(--$A$4),--$A$4,YEAR(TODAY()))),12,1),tb_pcm_custos[data_lancamento],"<="&EOMONTH(DATE(IF(N($A$4)>0,N($A$4),IF(ISNUMBER(--$A$4),--$A$4,YEAR(TODAY()))),12,1),0),tb_pcm_custos[categoria_custo],"MAO_OBRA",tb_pcm_custos[setor],$B$4)) | N17: =SUM(B17:M17) | O17: =N9-N17
A18: Terceiros | B18: =IF($B$4="",SUMIFS(tb_pcm_custos[valor_realizado],tb_pcm_custos[data_lancamento],">="&DATE(IF(N($A$4)>0,N($A$4),IF(ISNUMBER(--$A$4),--$A$4,YEAR(TODAY()))),1,1),tb_pcm_custos[data_lancamento],"<="&EOMONTH(DATE(IF(N($A$4)>0,N($A$4),IF(ISNUMBER(--$A$4),--$A$4,YEAR(TODAY()))),1,1),0),tb_pcm_custos[categoria_custo],"TERCEIROS"),SUMIFS(tb_pcm_custos[valor_realizado],tb_pcm_custos[data_lancamento],">="&DATE(IF(N($A$4)>0,N($A$4),IF(ISNUMBER(--$A$4),--$A$4,YEAR(TODAY()))),1,1),tb_pcm_custos[data_lancamento],"<="&EOMONTH(DATE(IF(N($A$4)>0,N($A$4),IF(ISNUMBER(--$A$4),--$A$4,YEAR(TODAY()))),1,1),0),tb_pcm_custos[categoria_custo],"TERCEIROS",tb_pcm_custos[setor],$B$4)) | C18: =IF($B$4="",SUMIFS(tb_pcm_custos[valor_realizado],tb_pcm_custos[data_lancamento],">="&DATE(IF(N($A$4)>0,N($A$4),IF(ISNUMBER(--$A$4),--$A$4,YEAR(TODAY()))),2,1),tb_pcm_custos[data_lancamento],"<="&EOMONTH(DATE(IF(N($A$4)>0,N($A$4),IF(ISNUMBER(--$A$4),--$A$4,YEAR(TODAY()))),2,1),0),tb_pcm_custos[categoria_custo],"TERCEIROS"),SUMIFS(tb_pcm_custos[valor_realizado],tb_pcm_custos[data_lancamento],">="&DATE(IF(N($A$4)>0,N($A$4),IF(ISNUMBER(--$A$4),--$A$4,YEAR(TODAY()))),2,1),tb_pcm_custos[data_lancamento],"<="&EOMONTH(DATE(IF(N($A$4)>0,N($A$4),IF(ISNUMBER(--$A$4),--$A$4,YEAR(TODAY()))),2,1),0),tb_pcm_custos[categoria_custo],"TERCEIROS",tb_pcm_custos[setor],$B$4)) | D18: =IF($B$4="",SUMIFS(tb_pcm_custos[valor_realizado],tb_pcm_custos[data_lancamento],">="&DATE(IF(N($A$4)>0,N($A$4),IF(ISNUMBER(--$A$4),--$A$4,YEAR(TODAY()))),3,1),tb_pcm_custos[data_lancamento],"<="&EOMONTH(DATE(IF(N($A$4)>0,N($A$4),IF(ISNUMBER(--$A$4),--$A$4,YEAR(TODAY()))),3,1),0),tb_pcm_custos[categoria_custo],"TERCEIROS"),SUMIFS(tb_pcm_custos[valor_realizado],tb_pcm_custos[data_lancamento],">="&DATE(IF(N($A$4)>0,N($A$4),IF(ISNUMBER(--$A$4),--$A$4,YEAR(TODAY()))),3,1),tb_pcm_custos[data_lancamento],"<="&EOMONTH(DATE(IF(N($A$4)>0,N($A$4),IF(ISNUMBER(--$A$4),--$A$4,YEAR(TODAY()))),3,1),0),tb_pcm_custos[categoria_custo],"TERCEIROS",tb_pcm_custos[setor],$B$4)) | E18: =IF($B$4="",SUMIFS(tb_pcm_custos[valor_realizado],tb_pcm_custos[data_lancamento],">="&DATE(IF(N($A$4)>0,N($A$4),IF(ISNUMBER(--$A$4),--$A$4,YEAR(TODAY()))),4,1),tb_pcm_custos[data_lancamento],"<="&EOMONTH(DATE(IF(N($A$4)>0,N($A$4),IF(ISNUMBER(--$A$4),--$A$4,YEAR(TODAY()))),4,1),0),tb_pcm_custos[categoria_custo],"TERCEIROS"),SUMIFS(tb_pcm_custos[valor_realizado],tb_pcm_custos[data_lancamento],">="&DATE(IF(N($A$4)>0,N($A$4),IF(ISNUMBER(--$A$4),--$A$4,YEAR(TODAY()))),4,1),tb_pcm_custos[data_lancamento],"<="&EOMONTH(DATE(IF(N($A$4)>0,N($A$4),IF(ISNUMBER(--$A$4),--$A$4,YEAR(TODAY()))),4,1),0),tb_pcm_custos[categoria_custo],"TERCEIROS",tb_pcm_custos[setor],$B$4)) | F18: =IF($B$4="",SUMIFS(tb_pcm_custos[valor_realizado],tb_pcm_custos[data_lancamento],">="&DATE(IF(N($A$4)>0,N($A$4),IF(ISNUMBER(--$A$4),--$A$4,YEAR(TODAY()))),5,1),tb_pcm_custos[data_lancamento],"<="&EOMONTH(DATE(IF(N($A$4)>0,N($A$4),IF(ISNUMBER(--$A$4),--$A$4,YEAR(TODAY()))),5,1),0),tb_pcm_custos[categoria_custo],"TERCEIROS"),SUMIFS(tb_pcm_custos[valor_realizado],tb_pcm_custos[data_lancamento],">="&DATE(IF(N($A$4)>0,N($A$4),IF(ISNUMBER(--$A$4),--$A$4,YEAR(TODAY()))),5,1),tb_pcm_custos[data_lancamento],"<="&EOMONTH(DATE(IF(N($A$4)>0,N($A$4),IF(ISNUMBER(--$A$4),--$A$4,YEAR(TODAY()))),5,1),0),tb_pcm_custos[categoria_custo],"TERCEIROS",tb_pcm_custos[setor],$B$4)) | G18: =IF($B$4="",SUMIFS(tb_pcm_custos[valor_realizado],tb_pcm_custos[data_lancamento],">="&DATE(IF(N($A$4)>0,N($A$4),IF(ISNUMBER(--$A$4),--$A$4,YEAR(TODAY()))),6,1),tb_pcm_custos[data_lancamento],"<="&EOMONTH(DATE(IF(N($A$4)>0,N($A$4),IF(ISNUMBER(--$A$4),--$A$4,YEAR(TODAY()))),6,1),0),tb_pcm_custos[categoria_custo],"TERCEIROS"),SUMIFS(tb_pcm_custos[valor_realizado],tb_pcm_custos[data_lancamento],">="&DATE(IF(N($A$4)>0,N($A$4),IF(ISNUMBER(--$A$4),--$A$4,YEAR(TODAY()))),6,1),tb_pcm_custos[data_lancamento],"<="&EOMONTH(DATE(IF(N($A$4)>0,N($A$4),IF(ISNUMBER(--$A$4),--$A$4,YEAR(TODAY()))),6,1),0),tb_pcm_custos[categoria_custo],"TERCEIROS",tb_pcm_custos[setor],$B$4)) | H18: =IF($B$4="",SUMIFS(tb_pcm_custos[valor_realizado],tb_pcm_custos[data_lancamento],">="&DATE(IF(N($A$4)>0,N($A$4),IF(ISNUMBER(--$A$4),--$A$4,YEAR(TODAY()))),7,1),tb_pcm_custos[data_lancamento],"<="&EOMONTH(DATE(IF(N($A$4)>0,N($A$4),IF(ISNUMBER(--$A$4),--$A$4,YEAR(TODAY()))),7,1),0),tb_pcm_custos[categoria_custo],"TERCEIROS"),SUMIFS(tb_pcm_custos[valor_realizado],tb_pcm_custos[data_lancamento],">="&DATE(IF(N($A$4)>0,N($A$4),IF(ISNUMBER(--$A$4),--$A$4,YEAR(TODAY()))),7,1),tb_pcm_custos[data_lancamento],"<="&EOMONTH(DATE(IF(N($A$4)>0,N($A$4),IF(ISNUMBER(--$A$4),--$A$4,YEAR(TODAY()))),7,1),0),tb_pcm_custos[categoria_custo],"TERCEIROS",tb_pcm_custos[setor],$B$4)) | I18: =IF($B$4="",SUMIFS(tb_pcm_custos[valor_realizado],tb_pcm_custos[data_lancamento],">="&DATE(IF(N($A$4)>0,N($A$4),IF(ISNUMBER(--$A$4),--$A$4,YEAR(TODAY()))),8,1),tb_pcm_custos[data_lancamento],"<="&EOMONTH(DATE(IF(N($A$4)>0,N($A$4),IF(ISNUMBER(--$A$4),--$A$4,YEAR(TODAY()))),8,1),0),tb_pcm_custos[categoria_custo],"TERCEIROS"),SUMIFS(tb_pcm_custos[valor_realizado],tb_pcm_custos[data_lancamento],">="&DATE(IF(N($A$4)>0,N($A$4),IF(ISNUMBER(--$A$4),--$A$4,YEAR(TODAY()))),8,1),tb_pcm_custos[data_lancamento],"<="&EOMONTH(DATE(IF(N($A$4)>0,N($A$4),IF(ISNUMBER(--$A$4),--$A$4,YEAR(TODAY()))),8,1),0),tb_pcm_custos[categoria_custo],"TERCEIROS",tb_pcm_custos[setor],$B$4)) | J18: =IF($B$4="",SUMIFS(tb_pcm_custos[valor_realizado],tb_pcm_custos[data_lancamento],">="&DATE(IF(N($A$4)>0,N($A$4),IF(ISNUMBER(--$A$4),--$A$4,YEAR(TODAY()))),9,1),tb_pcm_custos[data_lancamento],"<="&EOMONTH(DATE(IF(N($A$4)>0,N($A$4),IF(ISNUMBER(--$A$4),--$A$4,YEAR(TODAY()))),9,1),0),tb_pcm_custos[categoria_custo],"TERCEIROS"),SUMIFS(tb_pcm_custos[valor_realizado],tb_pcm_custos[data_lancamento],">="&DATE(IF(N($A$4)>0,N($A$4),IF(ISNUMBER(--$A$4),--$A$4,YEAR(TODAY()))),9,1),tb_pcm_custos[data_lancamento],"<="&EOMONTH(DATE(IF(N($A$4)>0,N($A$4),IF(ISNUMBER(--$A$4),--$A$4,YEAR(TODAY()))),9,1),0),tb_pcm_custos[categoria_custo],"TERCEIROS",tb_pcm_custos[setor],$B$4)) | K18: =IF($B$4="",SUMIFS(tb_pcm_custos[valor_realizado],tb_pcm_custos[data_lancamento],">="&DATE(IF(N($A$4)>0,N($A$4),IF(ISNUMBER(--$A$4),--$A$4,YEAR(TODAY()))),10,1),tb_pcm_custos[data_lancamento],"<="&EOMONTH(DATE(IF(N($A$4)>0,N($A$4),IF(ISNUMBER(--$A$4),--$A$4,YEAR(TODAY()))),10,1),0),tb_pcm_custos[categoria_custo],"TERCEIROS"),SUMIFS(tb_pcm_custos[valor_realizado],tb_pcm_custos[data_lancamento],">="&DATE(IF(N($A$4)>0,N($A$4),IF(ISNUMBER(--$A$4),--$A$4,YEAR(TODAY()))),10,1),tb_pcm_custos[data_lancamento],"<="&EOMONTH(DATE(IF(N($A$4)>0,N($A$4),IF(ISNUMBER(--$A$4),--$A$4,YEAR(TODAY()))),10,1),0),tb_pcm_custos[categoria_custo],"TERCEIROS",tb_pcm_custos[setor],$B$4)) | L18: =IF($B$4="",SUMIFS(tb_pcm_custos[valor_realizado],tb_pcm_custos[data_lancamento],">="&DATE(IF(N($A$4)>0,N($A$4),IF(ISNUMBER(--$A$4),--$A$4,YEAR(TODAY()))),11,1),tb_pcm_custos[data_lancamento],"<="&EOMONTH(DATE(IF(N($A$4)>0,N($A$4),IF(ISNUMBER(--$A$4),--$A$4,YEAR(TODAY()))),11,1),0),tb_pcm_custos[categoria_custo],"TERCEIROS"),SUMIFS(tb_pcm_custos[valor_realizado],tb_pcm_custos[data_lancamento],">="&DATE(IF(N($A$4)>0,N($A$4),IF(ISNUMBER(--$A$4),--$A$4,YEAR(TODAY()))),11,1),tb_pcm_custos[data_lancamento],"<="&EOMONTH(DATE(IF(N($A$4)>0,N($A$4),IF(ISNUMBER(--$A$4),--$A$4,YEAR(TODAY()))),11,1),0),tb_pcm_custos[categoria_custo],"TERCEIROS",tb_pcm_custos[setor],$B$4)) | M18: =IF($B$4="",SUMIFS(tb_pcm_custos[valor_realizado],tb_pcm_custos[data_lancamento],">="&DATE(IF(N($A$4)>0,N($A$4),IF(ISNUMBER(--$A$4),--$A$4,YEAR(TODAY()))),12,1),tb_pcm_custos[data_lancamento],"<="&EOMONTH(DATE(IF(N($A$4)>0,N($A$4),IF(ISNUMBER(--$A$4),--$A$4,YEAR(TODAY()))),12,1),0),tb_pcm_custos[categoria_custo],"TERCEIROS"),SUMIFS(tb_pcm_custos[valor_realizado],tb_pcm_custos[data_lancamento],">="&DATE(IF(N($A$4)>0,N($A$4),IF(ISNUMBER(--$A$4),--$A$4,YEAR(TODAY()))),12,1),tb_pcm_custos[data_lancamento],"<="&EOMONTH(DATE(IF(N($A$4)>0,N($A$4),IF(ISNUMBER(--$A$4),--$A$4,YEAR(TODAY()))),12,1),0),tb_pcm_custos[categoria_custo],"TERCEIROS",tb_pcm_custos[setor],$B$4)) | N18: =SUM(B18:M18) | O18: =N10-N18
A19: Outros | B19: =IF($B$4="",SUMIFS(tb_pcm_custos[valor_realizado],tb_pcm_custos[data_lancamento],">="&DATE(IF(N($A$4)>0,N($A$4),IF(ISNUMBER(--$A$4),--$A$4,YEAR(TODAY()))),1,1),tb_pcm_custos[data_lancamento],"<="&EOMONTH(DATE(IF(N($A$4)>0,N($A$4),IF(ISNUMBER(--$A$4),--$A$4,YEAR(TODAY()))),1,1),0),tb_pcm_custos[categoria_custo],"OUTROS"),SUMIFS(tb_pcm_custos[valor_realizado],tb_pcm_custos[data_lancamento],">="&DATE(IF(N($A$4)>0,N($A$4),IF(ISNUMBER(--$A$4),--$A$4,YEAR(TODAY()))),1,1),tb_pcm_custos[data_lancamento],"<="&EOMONTH(DATE(IF(N($A$4)>0,N($A$4),IF(ISNUMBER(--$A$4),--$A$4,YEAR(TODAY()))),1,1),0),tb_pcm_custos[categoria_custo],"OUTROS",tb_pcm_custos[setor],$B$4)) | C19: =IF($B$4="",SUMIFS(tb_pcm_custos[valor_realizado],tb_pcm_custos[data_lancamento],">="&DATE(IF(N($A$4)>0,N($A$4),IF(ISNUMBER(--$A$4),--$A$4,YEAR(TODAY()))),2,1),tb_pcm_custos[data_lancamento],"<="&EOMONTH(DATE(IF(N($A$4)>0,N($A$4),IF(ISNUMBER(--$A$4),--$A$4,YEAR(TODAY()))),2,1),0),tb_pcm_custos[categoria_custo],"OUTROS"),SUMIFS(tb_pcm_custos[valor_realizado],tb_pcm_custos[data_lancamento],">="&DATE(IF(N($A$4)>0,N($A$4),IF(ISNUMBER(--$A$4),--$A$4,YEAR(TODAY()))),2,1),tb_pcm_custos[data_lancamento],"<="&EOMONTH(DATE(IF(N($A$4)>0,N($A$4),IF(ISNUMBER(--$A$4),--$A$4,YEAR(TODAY()))),2,1),0),tb_pcm_custos[categoria_custo],"OUTROS",tb_pcm_custos[setor],$B$4)) | D19: =IF($B$4="",SUMIFS(tb_pcm_custos[valor_realizado],tb_pcm_custos[data_lancamento],">="&DATE(IF(N($A$4)>0,N($A$4),IF(ISNUMBER(--$A$4),--$A$4,YEAR(TODAY()))),3,1),tb_pcm_custos[data_lancamento],"<="&EOMONTH(DATE(IF(N($A$4)>0,N($A$4),IF(ISNUMBER(--$A$4),--$A$4,YEAR(TODAY()))),3,1),0),tb_pcm_custos[categoria_custo],"OUTROS"),SUMIFS(tb_pcm_custos[valor_realizado],tb_pcm_custos[data_lancamento],">="&DATE(IF(N($A$4)>0,N($A$4),IF(ISNUMBER(--$A$4),--$A$4,YEAR(TODAY()))),3,1),tb_pcm_custos[data_lancamento],"<="&EOMONTH(DATE(IF(N($A$4)>0,N($A$4),IF(ISNUMBER(--$A$4),--$A$4,YEAR(TODAY()))),3,1),0),tb_pcm_custos[categoria_custo],"OUTROS",tb_pcm_custos[setor],$B$4)) | E19: =IF($B$4="",SUMIFS(tb_pcm_custos[valor_realizado],tb_pcm_custos[data_lancamento],">="&DATE(IF(N($A$4)>0,N($A$4),IF(ISNUMBER(--$A$4),--$A$4,YEAR(TODAY()))),4,1),tb_pcm_custos[data_lancamento],"<="&EOMONTH(DATE(IF(N($A$4)>0,N($A$4),IF(ISNUMBER(--$A$4),--$A$4,YEAR(TODAY()))),4,1),0),tb_pcm_custos[categoria_custo],"OUTROS"),SUMIFS(tb_pcm_custos[valor_realizado],tb_pcm_custos[data_lancamento],">="&DATE(IF(N($A$4)>0,N($A$4),IF(ISNUMBER(--$A$4),--$A$4,YEAR(TODAY()))),4,1),tb_pcm_custos[data_lancamento],"<="&EOMONTH(DATE(IF(N($A$4)>0,N($A$4),IF(ISNUMBER(--$A$4),--$A$4,YEAR(TODAY()))),4,1),0),tb_pcm_custos[categoria_custo],"OUTROS",tb_pcm_custos[setor],$B$4)) | F19: =IF($B$4="",SUMIFS(tb_pcm_custos[valor_realizado],tb_pcm_custos[data_lancamento],">="&DATE(IF(N($A$4)>0,N($A$4),IF(ISNUMBER(--$A$4),--$A$4,YEAR(TODAY()))),5,1),tb_pcm_custos[data_lancamento],"<="&EOMONTH(DATE(IF(N($A$4)>0,N($A$4),IF(ISNUMBER(--$A$4),--$A$4,YEAR(TODAY()))),5,1),0),tb_pcm_custos[categoria_custo],"OUTROS"),SUMIFS(tb_pcm_custos[valor_realizado],tb_pcm_custos[data_lancamento],">="&DATE(IF(N($A$4)>0,N($A$4),IF(ISNUMBER(--$A$4),--$A$4,YEAR(TODAY()))),5,1),tb_pcm_custos[data_lancamento],"<="&EOMONTH(DATE(IF(N($A$4)>0,N($A$4),IF(ISNUMBER(--$A$4),--$A$4,YEAR(TODAY()))),5,1),0),tb_pcm_custos[categoria_custo],"OUTROS",tb_pcm_custos[setor],$B$4)) | G19: =IF($B$4="",SUMIFS(tb_pcm_custos[valor_realizado],tb_pcm_custos[data_lancamento],">="&DATE(IF(N($A$4)>0,N($A$4),IF(ISNUMBER(--$A$4),--$A$4,YEAR(TODAY()))),6,1),tb_pcm_custos[data_lancamento],"<="&EOMONTH(DATE(IF(N($A$4)>0,N($A$4),IF(ISNUMBER(--$A$4),--$A$4,YEAR(TODAY()))),6,1),0),tb_pcm_custos[categoria_custo],"OUTROS"),SUMIFS(tb_pcm_custos[valor_realizado],tb_pcm_custos[data_lancamento],">="&DATE(IF(N($A$4)>0,N($A$4),IF(ISNUMBER(--$A$4),--$A$4,YEAR(TODAY()))),6,1),tb_pcm_custos[data_lancamento],"<="&EOMONTH(DATE(IF(N($A$4)>0,N($A$4),IF(ISNUMBER(--$A$4),--$A$4,YEAR(TODAY()))),6,1),0),tb_pcm_custos[categoria_custo],"OUTROS",tb_pcm_custos[setor],$B$4)) | H19: =IF($B$4="",SUMIFS(tb_pcm_custos[valor_realizado],tb_pcm_custos[data_lancamento],">="&DATE(IF(N($A$4)>0,N($A$4),IF(ISNUMBER(--$A$4),--$A$4,YEAR(TODAY()))),7,1),tb_pcm_custos[data_lancamento],"<="&EOMONTH(DATE(IF(N($A$4)>0,N($A$4),IF(ISNUMBER(--$A$4),--$A$4,YEAR(TODAY()))),7,1),0),tb_pcm_custos[categoria_custo],"OUTROS"),SUMIFS(tb_pcm_custos[valor_realizado],tb_pcm_custos[data_lancamento],">="&DATE(IF(N($A$4)>0,N($A$4),IF(ISNUMBER(--$A$4),--$A$4,YEAR(TODAY()))),7,1),tb_pcm_custos[data_lancamento],"<="&EOMONTH(DATE(IF(N($A$4)>0,N($A$4),IF(ISNUMBER(--$A$4),--$A$4,YEAR(TODAY()))),7,1),0),tb_pcm_custos[categoria_custo],"OUTROS",tb_pcm_custos[setor],$B$4)) | I19: =IF($B$4="",SUMIFS(tb_pcm_custos[valor_realizado],tb_pcm_custos[data_lancamento],">="&DATE(IF(N($A$4)>0,N($A$4),IF(ISNUMBER(--$A$4),--$A$4,YEAR(TODAY()))),8,1),tb_pcm_custos[data_lancamento],"<="&EOMONTH(DATE(IF(N($A$4)>0,N($A$4),IF(ISNUMBER(--$A$4),--$A$4,YEAR(TODAY()))),8,1),0),tb_pcm_custos[categoria_custo],"OUTROS"),SUMIFS(tb_pcm_custos[valor_realizado],tb_pcm_custos[data_lancamento],">="&DATE(IF(N($A$4)>0,N($A$4),IF(ISNUMBER(--$A$4),--$A$4,YEAR(TODAY()))),8,1),tb_pcm_custos[data_lancamento],"<="&EOMONTH(DATE(IF(N($A$4)>0,N($A$4),IF(ISNUMBER(--$A$4),--$A$4,YEAR(TODAY()))),8,1),0),tb_pcm_custos[categoria_custo],"OUTROS",tb_pcm_custos[setor],$B$4)) | J19: =IF($B$4="",SUMIFS(tb_pcm_custos[valor_realizado],tb_pcm_custos[data_lancamento],">="&DATE(IF(N($A$4)>0,N($A$4),IF(ISNUMBER(--$A$4),--$A$4,YEAR(TODAY()))),9,1),tb_pcm_custos[data_lancamento],"<="&EOMONTH(DATE(IF(N($A$4)>0,N($A$4),IF(ISNUMBER(--$A$4),--$A$4,YEAR(TODAY()))),9,1),0),tb_pcm_custos[categoria_custo],"OUTROS"),SUMIFS(tb_pcm_custos[valor_realizado],tb_pcm_custos[data_lancamento],">="&DATE(IF(N($A$4)>0,N($A$4),IF(ISNUMBER(--$A$4),--$A$4,YEAR(TODAY()))),9,1),tb_pcm_custos[data_lancamento],"<="&EOMONTH(DATE(IF(N($A$4)>0,N($A$4),IF(ISNUMBER(--$A$4),--$A$4,YEAR(TODAY()))),9,1),0),tb_pcm_custos[categoria_custo],"OUTROS",tb_pcm_custos[setor],$B$4)) | K19: =IF($B$4="",SUMIFS(tb_pcm_custos[valor_realizado],tb_pcm_custos[data_lancamento],">="&DATE(IF(N($A$4)>0,N($A$4),IF(ISNUMBER(--$A$4),--$A$4,YEAR(TODAY()))),10,1),tb_pcm_custos[data_lancamento],"<="&EOMONTH(DATE(IF(N($A$4)>0,N($A$4),IF(ISNUMBER(--$A$4),--$A$4,YEAR(TODAY()))),10,1),0),tb_pcm_custos[categoria_custo],"OUTROS"),SUMIFS(tb_pcm_custos[valor_realizado],tb_pcm_custos[data_lancamento],">="&DATE(IF(N($A$4)>0,N($A$4),IF(ISNUMBER(--$A$4),--$A$4,YEAR(TODAY()))),10,1),tb_pcm_custos[data_lancamento],"<="&EOMONTH(DATE(IF(N($A$4)>0,N($A$4),IF(ISNUMBER(--$A$4),--$A$4,YEAR(TODAY()))),10,1),0),tb_pcm_custos[categoria_custo],"OUTROS",tb_pcm_custos[setor],$B$4)) | L19: =IF($B$4="",SUMIFS(tb_pcm_custos[valor_realizado],tb_pcm_custos[data_lancamento],">="&DATE(IF(N($A$4)>0,N($A$4),IF(ISNUMBER(--$A$4),--$A$4,YEAR(TODAY()))),11,1),tb_pcm_custos[data_lancamento],"<="&EOMONTH(DATE(IF(N($A$4)>0,N($A$4),IF(ISNUMBER(--$A$4),--$A$4,YEAR(TODAY()))),11,1),0),tb_pcm_custos[categoria_custo],"OUTROS"),SUMIFS(tb_pcm_custos[valor_realizado],tb_pcm_custos[data_lancamento],">="&DATE(IF(N($A$4)>0,N($A$4),IF(ISNUMBER(--$A$4),--$A$4,YEAR(TODAY()))),11,1),tb_pcm_custos[data_lancamento],"<="&EOMONTH(DATE(IF(N($A$4)>0,N($A$4),IF(ISNUMBER(--$A$4),--$A$4,YEAR(TODAY()))),11,1),0),tb_pcm_custos[categoria_custo],"OUTROS",tb_pcm_custos[setor],$B$4)) | M19: =IF($B$4="",SUMIFS(tb_pcm_custos[valor_realizado],tb_pcm_custos[data_lancamento],">="&DATE(IF(N($A$4)>0,N($A$4),IF(ISNUMBER(--$A$4),--$A$4,YEAR(TODAY()))),12,1),tb_pcm_custos[data_lancamento],"<="&EOMONTH(DATE(IF(N($A$4)>0,N($A$4),IF(ISNUMBER(--$A$4),--$A$4,YEAR(TODAY()))),12,1),0),tb_pcm_custos[categoria_custo],"OUTROS"),SUMIFS(tb_pcm_custos[valor_realizado],tb_pcm_custos[data_lancamento],">="&DATE(IF(N($A$4)>0,N($A$4),IF(ISNUMBER(--$A$4),--$A$4,YEAR(TODAY()))),12,1),tb_pcm_custos[data_lancamento],"<="&EOMONTH(DATE(IF(N($A$4)>0,N($A$4),IF(ISNUMBER(--$A$4),--$A$4,YEAR(TODAY()))),12,1),0),tb_pcm_custos[categoria_custo],"OUTROS",tb_pcm_custos[setor],$B$4)) | N19: =SUM(B19:M19) | O19: =N11-N19
A20: Total do mês | B20: =SUM(B16:B19) | C20: =SUM(C16:C19) | D20: =SUM(D16:D19) | E20: =SUM(E16:E19) | F20: =SUM(F16:F19) | G20: =SUM(G16:G19) | H20: =SUM(H16:H19) | I20: =SUM(I16:I19) | ... N20: =SUM(N16:N19) | O20: =N12-N20
A22: Orçado x realizado por mês total de todas as categorias (R$)
A38: ● % usado até 90% ● de 90% a 100% ● acima do orçado Categorias iguais às da aba Lançamentos. Ano em branco = ano atual.

Sheet Lançamentos
B1: Lançamentos | G1: ="Rev. "&'Leia-me'!$D$15&" · "&'Leia-me'!$D$16
B2: Objetivo: Uma linha por custo: data, TAG, setor, categoria e valor | G2: ="Elaborado: "&'Leia-me'!$D$13&" · Aprovado: "&'Leia-me'!$D$14
A3: Referência do lançamento | B3: Data do custo | C3: TAG ▼ | D3: Equipamento | E3: Setor de apropriação ▼ | F3: Categoria ▼ | G3: Custo realizado | H3: Documento de origem
A4: referencia_lancamento | B4: data_lancamento | C4: tag | D4: equipamento | E4: setor | F4: categoria_custo | G4: valor_realizado | H4: documento_origem
D5: =IF(C5="","",IFERROR(INDEX(tb_pcm_ativos[descricao_ativo],MATCH(C5,tb_pcm_ativos[tag],0)),"fora do cadastro"))
D6: =IF(C6="","",IFERROR(INDEX(tb_pcm_ativos[descricao_ativo],MATCH(C6,tb_pcm_ativos[tag],0)),"fora do cadastro"))
D7: =IF(C7="","",IFERROR(INDEX(tb_pcm_ativos[descricao_ativo],MATCH(C7,tb_pcm_ativos[tag],0)),"fora do cadastro"))
D8: =IF(C8="","",IFERROR(INDEX(tb_pcm_ativos[descricao_ativo],MATCH(C8,tb_pcm_ativos[tag],0)),"fora do cadastro"))
D9: =IF(C9="","",IFERROR(INDEX(tb_pcm_ativos[descricao_ativo],MATCH(C9,tb_pcm_ativos[tag],0)),"fora do cadastro"))
D10: =IF(C10="","",IFERROR(INDEX(tb_pcm_ativos[descricao_ativo],MATCH(C10,tb_pcm_ativos[tag],0)),"fora do cadastro"))
D11: =IF(C11="","",IFERROR(INDEX(tb_pcm_ativos[descricao_ativo],MATCH(C11,tb_pcm_ativos[tag],0)),"fora do cadastro"))
D12: =IF(C12="","",IFERROR(INDEX(tb_pcm_ativos[descricao_ativo],MATCH(C12,tb_pcm_ativos[tag],0)),"fora do cadastro"))
D13: =IF(C13="","",IFERROR(INDEX(tb_pcm_ativos[descricao_ativo],MATCH(C13,tb_pcm_ativos[tag],0)),"fora do cadastro"))
D14: =IF(C14="","",IFERROR(INDEX(tb_pcm_ativos[descricao_ativo],MATCH(C14,tb_pcm_ativos[tag],0)),"fora do cadastro"))
D15: =IF(C15="","",IFERROR(INDEX(tb_pcm_ativos[descricao_ativo],MATCH(C15,tb_pcm_ativos[tag],0)),"fora do cadastro"))
D16: =IF(C16="","",IFERROR(INDEX(tb_pcm_ativos[descricao_ativo],MATCH(C16,tb_pcm_ativos[tag],0)),"fora do cadastro"))
... D29: =IF(C29="","",IFERROR(INDEX(tb_pcm_ativos[descricao_ativo],MATCH(C29,tb_pcm_ativos[tag],0)),"fora do cadastro"))

Sheet Cadastros
C1: Cadastros | G1: ="Rev. "&'Leia-me'!$D$15&" · "&'Leia-me'!$D$16
C2: Objetivo: Cadastre aqui os itens usados nas listas (▼) das outras abas. | G2: ="Elaborado: "&'Leia-me'!$D$13&" · Aprovado: "&'Leia-me'!$D$14
A3: TAG | B3: Equipamento | C3: Família de equipamento ▼ | D3: Setor ▼ | F3: Setor | H3: Família de equipamento
A4: tag | B4: descricao_ativo | C4: familia | D4: setor | F4: nome_setor | H4: nome_familia

Sheet Revisões
C1: Revisões | D1: ="Rev. "&'Leia-me'!$D$15&" · "&'Leia-me'!$D$16
C2: Objetivo: Registre cada alteração do modelo; a última linha alimenta Rev. e data do cabeçalho. | D2: ="Elaborado: "&'Leia-me'!$D$13&" · Aprovado: "&'Leia-me'!$D$14
A3: Rev | B3: Data | C3: Descrição da alteração | D3: Elaborado por | E3: Aprovado por
A4: revisao | B4: data_revisao | C4: descricao_alteracao | D4: elaborado_por | E4: aprovado_por
A5: 00 | B5: 46325 | C5: Emissão inicial
